{
    "Goth": {
      "maschio": { "padre": "Ethan", "madre": "Raven", "fratello": "Sebastian" },
      "femmina": { "padre": "Ethan", "madre": "Raven", "sorella": "Lilith" }
    },
    "Metallaro": {
      "maschio": { "madre": "Isabella", "fratello": "Axel" },
      "femmina": { "madre": "Isabella", "sorella": "Scarlett" }
    },
    "Nerd": {
      "maschio": { "padre": "William", "madre": "Sophia", "sorella": "Emily" },
      "femmina": { "padre": "William", "madre": "Sophia", "fratello": "Lucas" }
    },
    "Tabboz": {
      "maschio": { "padre": "Brandon", "fratello": "Derek" },
      "femmina": { "madre": "Jessica", "sorella": "Vanessa" }
    },
    "Sportivo": {
      "maschio": { "padre": "Michael", "madre": "Linda", "fratello": "Connor" },
      "femmina": { "padre": "Michael", "madre": "Linda", "sorella": "Brooke" }
    }
  }
  